<?xml version="1.0" encoding="UTF-8"?>
<!DOCTYPE mapper PUBLIC "-//mybatis.org//DTD Mapper 3.0//EN" "http://mybatis.org/dtd/mybatis-3-mapper.dtd">
<mapper namespace="com.njpes.www.dao.workschedule.JobCongressMapper">
  <resultMap id="BaseResultMap" type="com.njpes.www.entity.workschedule.JobCongress">
    <!--
      WARNING - @mbggenerated
      This element is automatically generated by MyBatis Generator, do not modify.
      This element was generated on Sun Jul 19 02:00:25 CST 2015.
    -->
    <id column="id" jdbcType="BIGINT" property="id" />
    <result column="starttime" jdbcType="TIMESTAMP" property="starttime" />
    <result column="endtime" jdbcType="TIMESTAMP" property="endtime" />
    <result column="emcee" jdbcType="VARCHAR" property="emcee" />
    <result column="recordperson" jdbcType="VARCHAR" property="recordperson" />
    <result column="share" jdbcType="BIT" property="share" />
    <result column="place" jdbcType="VARCHAR" property="place" />
    <result column="dep" jdbcType="BIGINT" property="dep" />
    <result column="write_time" jdbcType="TIMESTAMP" property="writeTime" />
    <result column="author" jdbcType="BIGINT" property="author" />
  </resultMap>
  <resultMap extends="BaseResultMap" id="ResultMapWithBLOBs" type="com.njpes.www.entity.workschedule.JobCongressWithBLOBs">
    <!--
      WARNING - @mbggenerated
      This element is automatically generated by MyBatis Generator, do not modify.
      This element was generated on Sun Jul 19 02:00:25 CST 2015.
    -->
    <result column="subject" jdbcType="LONGVARCHAR" property="subject" />
    <result column="persons" jdbcType="LONGVARCHAR" property="persons" />
    <result column="content" jdbcType="LONGVARCHAR" property="content" />
    <result column="specailrecord" jdbcType="LONGVARCHAR" property="specailrecord" />
    <result column="otherpersons" jdbcType="LONGVARCHAR" property="otherpersons" />
  </resultMap>
  <sql id="Base_Column_List">
    <!--
      WARNING - @mbggenerated
      This element is automatically generated by MyBatis Generator, do not modify.
      This element was generated on Sun Jul 19 02:00:25 CST 2015.
    -->
    id, starttime, endtime, emcee, recordperson, share, place, dep, write_time, author
  </sql>
  <sql id="Blob_Column_List">
    <!--
      WARNING - @mbggenerated
      This element is automatically generated by MyBatis Generator, do not modify.
      This element was generated on Sun Jul 19 02:00:25 CST 2015.
    -->
    subject, persons, content, specailrecord, otherpersons
  </sql>
  <select id="selectByPrimaryKey" parameterType="java.lang.Long" resultMap="ResultMapWithBLOBs">
    <!--
      WARNING - @mbggenerated
      This element is automatically generated by MyBatis Generator, do not modify.
      This element was generated on Sun Jul 19 02:00:25 CST 2015.
    -->
    select 
    <include refid="Base_Column_List" />
    ,
    <include refid="Blob_Column_List" />
    from job_congress
    where id = #{id,jdbcType=BIGINT}
  </select>
  <delete id="deleteByPrimaryKey" parameterType="java.lang.Long">
    <!--
      WARNING - @mbggenerated
      This element is automatically generated by MyBatis Generator, do not modify.
      This element was generated on Sun Jul 19 02:00:25 CST 2015.
    -->
    delete from job_congress
    where id = #{id,jdbcType=BIGINT}
  </delete>
  <insert id="insert" parameterType="com.njpes.www.entity.workschedule.JobCongressWithBLOBs" useGeneratedKeys="true" keyProperty="id">
    <!--
      WARNING - @mbggenerated
      This element is automatically generated by MyBatis Generator, do not modify.
      This element was generated on Sun Jul 19 02:00:25 CST 2015.
    -->
    insert into job_congress (id, starttime, endtime, 
      emcee, recordperson, share, 
      place, dep, write_time, 
      author, subject, persons, 
      content, specailrecord, otherpersons
      )
    values (#{id,jdbcType=BIGINT}, #{starttime,jdbcType=TIMESTAMP}, #{endtime,jdbcType=TIMESTAMP}, 
      #{emcee,jdbcType=VARCHAR}, #{recordperson,jdbcType=VARCHAR}, #{share,jdbcType=BIT}, 
      #{place,jdbcType=VARCHAR}, #{dep,jdbcType=BIGINT}, #{writeTime,jdbcType=TIMESTAMP}, 
      #{author,jdbcType=BIGINT}, #{subject,jdbcType=LONGVARCHAR}, #{persons,jdbcType=LONGVARCHAR}, 
      #{content,jdbcType=LONGVARCHAR}, #{specailrecord,jdbcType=LONGVARCHAR}, #{otherpersons,jdbcType=LONGVARCHAR}
      )
  </insert>
  <insert id="insertSelective" parameterType="com.njpes.www.entity.workschedule.JobCongressWithBLOBs" useGeneratedKeys="true" keyProperty="id">
    <!--
      WARNING - @mbggenerated
      This element is automatically generated by MyBatis Generator, do not modify.
      This element was generated on Sun Jul 19 02:00:25 CST 2015.
    -->
    insert into job_congress
    <trim prefix="(" suffix=")" suffixOverrides=",">
      <if test="id != null">
        id,
      </if>
      <if test="starttime != null">
        starttime,
      </if>
      <if test="endtime != null">
        endtime,
      </if>
      <if test="emcee != null">
        emcee,
      </if>
      <if test="recordperson != null">
        recordperson,
      </if>
      <if test="share != null">
        share,
      </if>
      <if test="place != null">
        place,
      </if>
      <if test="dep != null">
        dep,
      </if>
      <if test="writeTime != null">
        write_time,
      </if>
      <if test="author != null">
        author,
      </if>
      <if test="subject != null">
        subject,
      </if>
      <if test="persons != null">
        persons,
      </if>
      <if test="content != null">
        content,
      </if>
      <if test="specailrecord != null">
        specailrecord,
      </if>
      <if test="otherpersons != null">
        otherpersons,
      </if>
    </trim>
    <trim prefix="values (" suffix=")" suffixOverrides=",">
      <if test="id != null">
        #{id,jdbcType=BIGINT},
      </if>
      <if test="starttime != null">
        #{starttime,jdbcType=TIMESTAMP},
      </if>
      <if test="endtime != null">
        #{endtime,jdbcType=TIMESTAMP},
      </if>
      <if test="emcee != null">
        #{emcee,jdbcType=VARCHAR},
      </if>
      <if test="recordperson != null">
        #{recordperson,jdbcType=VARCHAR},
      </if>
      <if test="share != null">
        #{share,jdbcType=BIT},
      </if>
      <if test="place != null">
        #{place,jdbcType=VARCHAR},
      </if>
      <if test="dep != null">
        #{dep,jdbcType=BIGINT},
      </if>
      <if test="writeTime != null">
        #{writeTime,jdbcType=TIMESTAMP},
      </if>
      <if test="author != null">
        #{author,jdbcType=BIGINT},
      </if>
      <if test="subject != null">
        #{subject,jdbcType=LONGVARCHAR},
      </if>
      <if test="persons != null">
        #{persons,jdbcType=LONGVARCHAR},
      </if>
      <if test="content != null">
        #{content,jdbcType=LONGVARCHAR},
      </if>
      <if test="specailrecord != null">
        #{specailrecord,jdbcType=LONGVARCHAR},
      </if>
      <if test="otherpersons != null">
        #{otherpersons,jdbcType=LONGVARCHAR},
      </if>
    </trim>
  </insert>
  <update id="updateByPrimaryKeySelective" parameterType="com.njpes.www.entity.workschedule.JobCongressWithBLOBs">
    <!--
      WARNING - @mbggenerated
      This element is automatically generated by MyBatis Generator, do not modify.
      This element was generated on Sun Jul 19 02:00:25 CST 2015.
    -->
    update job_congress
    <set>
      <if test="starttime != null">
        starttime = #{starttime,jdbcType=TIMESTAMP},
      </if>
      <if test="endtime != null">
        endtime = #{endtime,jdbcType=TIMESTAMP},
      </if>
      <if test="emcee != null">
        emcee = #{emcee,jdbcType=VARCHAR},
      </if>
      <if test="recordperson != null">
        recordperson = #{recordperson,jdbcType=VARCHAR},
      </if>
      <if test="share != null">
        share = #{share,jdbcType=BIT},
      </if>
      <if test="place != null">
        place = #{place,jdbcType=VARCHAR},
      </if>
      <if test="dep != null">
        dep = #{dep,jdbcType=BIGINT},
      </if>
      <if test="writeTime != null">
        write_time = #{writeTime,jdbcType=TIMESTAMP},
      </if>
      <if test="author != null">
        author = #{author,jdbcType=BIGINT},
      </if>
      <if test="subject != null">
        subject = #{subject,jdbcType=LONGVARCHAR},
      </if>
      <if test="persons != null">
        persons = #{persons,jdbcType=LONGVARCHAR},
      </if>
      <if test="content != null">
        content = #{content,jdbcType=LONGVARCHAR},
      </if>
      <if test="specailrecord != null">
        specailrecord = #{specailrecord,jdbcType=LONGVARCHAR},
      </if>
      <if test="otherpersons != null">
        otherpersons = #{otherpersons,jdbcType=LONGVARCHAR},
      </if>
    </set>
    where id = #{id,jdbcType=BIGINT}
  </update>
  <update id="updateByPrimaryKeyWithBLOBs" parameterType="com.njpes.www.entity.workschedule.JobCongressWithBLOBs">
    <!--
      WARNING - @mbggenerated
      This element is automatically generated by MyBatis Generator, do not modify.
      This element was generated on Sun Jul 19 02:00:25 CST 2015.
    -->
    update job_congress
    set starttime = #{starttime,jdbcType=TIMESTAMP},
      endtime = #{endtime,jdbcType=TIMESTAMP},
      emcee = #{emcee,jdbcType=VARCHAR},
      recordperson = #{recordperson,jdbcType=VARCHAR},
      share = #{share,jdbcType=BIT},
      place = #{place,jdbcType=VARCHAR},
      dep = #{dep,jdbcType=BIGINT},
      write_time = #{writeTime,jdbcType=TIMESTAMP},
      author = #{author,jdbcType=BIGINT},
      subject = #{subject,jdbcType=LONGVARCHAR},
      persons = #{persons,jdbcType=LONGVARCHAR},
      content = #{content,jdbcType=LONGVARCHAR},
      specailrecord = #{specailrecord,jdbcType=LONGVARCHAR},
      otherpersons = #{otherpersons,jdbcType=LONGVARCHAR}
    where id = #{id,jdbcType=BIGINT}
  </update>
  <update id="updateByPrimaryKey" parameterType="com.njpes.www.entity.workschedule.JobCongress">
    <!--
      WARNING - @mbggenerated
      This element is automatically generated by MyBatis Generator, do not modify.
      This element was generated on Sun Jul 19 02:00:25 CST 2015.
    -->
    update job_congress
    set starttime = #{starttime,jdbcType=TIMESTAMP},
      endtime = #{endtime,jdbcType=TIMESTAMP},
      emcee = #{emcee,jdbcType=VARCHAR},
      recordperson = #{recordperson,jdbcType=VARCHAR},
      share = #{share,jdbcType=BIT},
      place = #{place,jdbcType=VARCHAR},
      dep = #{dep,jdbcType=BIGINT},
      write_time = #{writeTime,jdbcType=TIMESTAMP},
      author = #{author,jdbcType=BIGINT}
    where id = #{id,jdbcType=BIGINT}
  </update>
  <select id="findByPage" resultMap="ResultMapWithBLOBs">
  	select 
    <include refid="Base_Column_List" />
    ,
    <include refid="Blob_Column_List" />
    from job_congress
    <where>
    	<if test="entity.subject !=null and entity.subject !=''">
    		and subject like concat('%',#{entity.subject,jdbcType=LONGVARCHAR},'%')
    	</if>
    	<if test="entity.place !=null and entity.place !=''">
    		and place like concat('%',#{entity.place,jdbcType=VARCHAR},'%')
    	</if>
    	<if test="entity.emcee !=null and entity.emcee !=''">
    		and emcee like concat('%',#{entity.emcee,jdbcType=VARCHAR},'%')
    	</if>
    	<if test="entity.recordperson !=null and entity.recordperson !=''">
    		and recordperson like concat('%',#{entity.recordperson,jdbcType=VARCHAR},'%')
    	</if>
    	<if test="entity.starttime !=null">
    		<![CDATA[
    			and starttime >= #{entity.starttime,jdbcType=TIMESTAMP}
    		]]>
    	</if>
    	<if test="entity.dep !=null and entity.dep >0">
    		and dep = #{entity.dep,jdbcType=BIGINT}
    	</if>
    </where>
    order by write_time desc
  </select>
</mapper>