<?xml version="1.0" encoding="UTF-8"?>
<!DOCTYPE mapper PUBLIC "-//mybatis.org//DTD Mapper 3.0//EN" "http://mybatis.org/dtd/mybatis-3-mapper.dtd">
<mapper namespace="com.njpes.www.dao.baseinfo.OrganizationLevelMapper">
  <resultMap id="BaseResultMap" type="com.njpes.www.entity.baseinfo.organization.OrganizationLevel">
    <!--
      WARNING - @mbggenerated
      This element is automatically generated by MyBatis Generator, do not modify.
      This element was generated on Tue May 19 00:07:11 CST 2015.
    -->
    <id column="id" jdbcType="INTEGER" property="id" />
    <result column="name" jdbcType="VARCHAR" property="name" />
  </resultMap>
  <sql id="Base_Column_List">
    <!--
      WARNING - @mbggenerated
      This element is automatically generated by MyBatis Generator, do not modify.
      This element was generated on Tue May 19 00:07:11 CST 2015.
    -->
    id, name
  </sql>
  <select id="selectByPrimaryKey" parameterType="java.lang.Integer" resultMap="BaseResultMap">
    <!--
      WARNING - @mbggenerated
      This element is automatically generated by MyBatis Generator, do not modify.
      This element was generated on Tue May 19 00:07:11 CST 2015.
    -->
    select 
    <include refid="Base_Column_List" />
    from dic_organizationlevel
    where id = #{id,jdbcType=INTEGER}
  </select>
  <delete id="deleteByPrimaryKey" parameterType="java.lang.Integer">
    <!--
      WARNING - @mbggenerated
      This element is automatically generated by MyBatis Generator, do not modify.
      This element was generated on Tue May 19 00:07:11 CST 2015.
    -->
    delete from dic_organizationlevel
    where id = #{id,jdbcType=INTEGER}
  </delete>
  <insert id="insert" parameterType="com.njpes.www.entity.baseinfo.organization.OrganizationLevel">
    <!--
      WARNING - @mbggenerated
      This element is automatically generated by MyBatis Generator, do not modify.
      This element was generated on Tue May 19 00:07:11 CST 2015.
    -->
    insert into dic_organizationlevel (id, name)
    values (#{id,jdbcType=INTEGER}, #{name,jdbcType=VARCHAR})
  </insert>
  <insert id="insertSelective" parameterType="com.njpes.www.entity.baseinfo.organization.OrganizationLevel">
    <!--
      WARNING - @mbggenerated
      This element is automatically generated by MyBatis Generator, do not modify.
      This element was generated on Tue May 19 00:07:11 CST 2015.
    -->
    insert into dic_organizationlevel
    <trim prefix="(" suffix=")" suffixOverrides=",">
      <if test="id != null">
        id,
      </if>
      <if test="name != null">
        name,
      </if>
    </trim>
    <trim prefix="values (" suffix=")" suffixOverrides=",">
      <if test="id != null">
        #{id,jdbcType=INTEGER},
      </if>
      <if test="orglevelname != null">
        #{name,jdbcType=VARCHAR},
      </if>
    </trim>
  </insert>
  <update id="updateByPrimaryKeySelective" parameterType="com.njpes.www.entity.baseinfo.organization.OrganizationLevel">
    <!--
      WARNING - @mbggenerated
      This element is automatically generated by MyBatis Generator, do not modify.
      This element was generated on Tue May 19 00:07:11 CST 2015.
    -->
    update dic_organizationlevel
    <set>
      <if test="name != null">
        name = #{orglevelname,jdbcType=VARCHAR},
      </if>
    </set>
    where id = #{id,jdbcType=INTEGER}
  </update>
  <update id="updateByPrimaryKey" parameterType="com.njpes.www.entity.baseinfo.organization.OrganizationLevel">
    <!--
      WARNING - @mbggenerated
      This element is automatically generated by MyBatis Generator, do not modify.
      This element was generated on Tue May 19 00:07:11 CST 2015.
    -->
    update dic_organizationlevel
    set name = #{name,jdbcType=VARCHAR}
    where id = #{id,jdbcType=INTEGER}
  </update>
	<!-- 下面有可能需要根据用户的角色进行过滤  预留 -->
	<select id="selectAllOrgLevel" resultMap="BaseResultMap">
		select * from dic_organizationlevel
	</select>
	<select id="selectOrgLevelInCurentLevel" resultMap="BaseResultMap">
		select <include refid="Base_Column_List" /> from dic_organizationlevel 
		<where>
			<if test="current != null and current >0 and includemyself==false" >id>#{current,jdbcType=INTEGER}</if>
			<if test="current != null and current >0 and includemyself==true"  >id>=#{current,jdbcType=INTEGER} </if>
			<if test="includeschoollevel == false">
				and id &lt;&gt;6
			</if>
		</where> 
	</select>
	<select id="selectOrgDirectLevelInCurentLevel" resultMap="BaseResultMap">
	select <include refid="Base_Column_List" /> from dic_organizationlevel 
		<where>
			<if test="current != null and current >0 and includemyself==false" >id=#{current,jdbcType=INTEGER} +1</if>
			<if test="current != null and current >0 and includemyself==true"  >id=#{current,jdbcType=INTEGER} or  id=#{current,jdbcType=INTEGER} +1</if>
			<if test="includeschoollevel == true">
				or id =6
			</if>
		</where> 
	</select>
</mapper>